radicale_modoboa_auth_oauth2/__init__.py
radicale_modoboa_auth_oauth2/version.py
radicale_modoboa_auth_oauth2-0.4.0.dist-info/licenses/LICENSE
radicale_modoboa_auth_oauth2-0.4.0.dist-info/METADATA
radicale_modoboa_auth_oauth2-0.4.0.dist-info/WHEEL
radicale_modoboa_auth_oauth2-0.4.0.dist-info/top_level.txt
radicale_modoboa_auth_oauth2-0.4.0.dist-info/RECORD
