Metadata-Version: 2.4
Name: radicale_modoboa_auth_oauth2
Version: 0.4.0
Summary: Radicale plugin for oauth2 introspection based authentication
Author-email: Antoine Nguyen <tonio@ngyn.org>
License: MIT License
Project-URL: Repository, https://github.com/modoboa/radicale-modoboa-auth-oauth2
Project-URL: Issues, https://github.com/modoboa/radicale-modoboa-auth-oauth2/issues
Keywords: radicale,modoboa,oauth2,introspection
Classifier: Programming Language :: Python
Classifier: Development Status :: 5 - Production/Stable
Classifier: License :: OSI Approved :: MIT License
Classifier: Operating System :: OS Independent
Classifier: Programming Language :: Python :: 3
Requires-Python: >=3.9
License-File: LICENSE
Requires-Dist: Radicale
Requires-Dist: requests
Dynamic: license-file
